trek/__init__.py
trek/configuration.py
trek/database_providers.py
trek/file_manager.py
trek/logger.py
trek/main.py
trek/migration_manager.py
trek/migration_runner.py
trek/models.py
trek/templates/__Migrations.sql
trek/utils.py
db_trek-0.1.2.dist-info/entry_points.txt
db_trek-0.1.2.dist-info/WHEEL
db_trek-0.1.2.dist-info/METADATA
db_trek-0.1.2.dist-info/RECORD
