Metadata-Version: 2.1
Name: db-trek
Version: 0.1.2
Summary: 
Home-page: https://github.com/mr-katsini/trek
Author: Jon Katsini
Author-email: jon@greeff-katsini.co.za
Requires-Python: >=3.8,<4.0
Classifier: Programming Language :: Python :: 3
Classifier: Programming Language :: Python :: 3.8
Classifier: Programming Language :: Python :: 3.9
Requires-Dist: colorama (>=0.4.4,<0.5.0)
Requires-Dist: pyodbc (>=4.0.30,<5.0.0)
Requires-Dist: structlog (>=20.1.0,<21.0.0)
Project-URL: Documentation, https://github.com/mr-katsini/trek
Project-URL: Repository, https://github.com/mr-katsini/trek
